ophpy/2Dimage.py
ophpy/Depthmap.py
ophpy/Image2D.py
ophpy/PointCloud.py
ophpy/PointCloud_multicore.py
ophpy/__init__.py
ophpy-0.0.3.dist-info/LICENSE
ophpy-0.0.3.dist-info/METADATA
ophpy-0.0.3.dist-info/WHEEL
ophpy-0.0.3.dist-info/top_level.txt
ophpy-0.0.3.dist-info/RECORD
